vee/__init__.py
vee/main.py
victor_executable_experiment-0.1.0.dist-info/METADATA
victor_executable_experiment-0.1.0.dist-info/WHEEL
victor_executable_experiment-0.1.0.dist-info/entry_points.txt
victor_executable_experiment-0.1.0.dist-info/top_level.txt
victor_executable_experiment-0.1.0.dist-info/RECORD
